decospector/__init__.py
decospector/decospector.py
decospector/inspector.py
decospector-0.0.0.dist-info/METADATA
decospector-0.0.0.dist-info/WHEEL
decospector-0.0.0.dist-info/top_level.txt
decospector-0.0.0.dist-info/RECORD
